gate.v
`timescale 100ps/100ps

module Buf (i, o);

	input i;
	output o;

	buf A1(o, i);

endmodule

module Not (i, o);

	input i;
	output o;

	not A1(o, i);

endmodule

module And (i1, i2, o);

	input i1, i2;
	output o;

	and A1(o, i1, i2);

endmodule

module Or (i1, i2, o);

	input i1, i2;
	output o;

	or A1(o, i1, i2);

endmodule

module Nor (i1, i2, o);

	input i1, i2;
	output o;

	nor A1(o, i1, i2);

endmodule

module Nand (i1, i2, o);

	input i1, i2;
	output o;

	nand A1(o, i1, i2);

endmodule

module Xor (i1, i2, o);

	input i1, i2;
	output o;

	xor A1(o, i1, i2);

endmodule

module Xnor (i1, i2, o);

	input i1, i2;
	output o;

	xnor A1(o, i1, i2);

endmodule

// module gate;

// 	wire i1, i2, oBuf, oNot, oAnd, oOr, oNor, oNand, oXor, oXnor;
//    	integer i;
//    	integer k=0;
//    	parameter arr = 8'b00011011;/*or reg [15:0] arr = 8'b00011011 */

//    	assign {i1, i2} = k;
//    	Buf B1(i1, oBuf);
//    	Not N1(i1, oNot);
//    	And A1(i1, i2, oAnd);
//    	Or O1(i1, i2, oOr);
//    	Nor No1(i1, i2, oNor);
//    	Nand Na1(i1, i2, oNand);
//    	Xor X1(i1, i2, oXor);
//    	Xnor Xn1(i1, i2, oXnor);

// 	initial begin

// 		$dumpfile("gate.vcd");
// 		$dumpvars(0, gate);

// 		for(i=3;i>=0;i=i-1) begin
// 			k[0] = arr[2*i];
// 			k[1] = arr[2*i+1];
// 			#50 $display("done testing case %d", i);
// 		end

// 		$finish;

// 	end

// endmodule

flipflop.v
`timescale 100ps/100ps
`include "gate.v"

module SR (s, r, q, qp);

	input s, r;
	output q, qp;

	nor N1(q, clr, r, qp);
	nor N2(qp, pre, s, q);

endmodule

module D_no_trig (clock, d, q, qp);

	input clock, d;
	output q, qp;
	wire s, r;

	And A1(clock, d, s);
	And A2(clock, ~d, r);
	SR S1(s, r, q, qp);

endmodule

module D (clock, d, q, qp);

	input clock, d;
	output q, qp;
	wire d2;

	D_no_trig D1(~clock, d, d2, );
	D_no_trig D2(clock, d2, q, qp);


endmodule

module JK (clock, j, k, q, qp);

	input clock, j, k;
	output q, qp;
	wire j1, k1, d;

	And A1(j, qp, j1);
	And A2(~k, q, k1);
	Or O1(j1, k1, d);
	D D1(clock, d, q, qp);

endmodule

module D_preset (clock, d, pre, clr, q, qp);

	input clock, d, pre, clr;
	output reg q, qp;

	always @(posedge clock or posedge clr or posedge pre) begin
		if (clr) begin
			q <= 0;
		end
		else if (pre) begin
			q <= 1;
		end
		else begin
			q <= d;
		end
		qp <= ~q;
	end

endmodule

module flipflop;

	//####### setting circuits #########
	wire clock, j, kf, q, qp;

	JK J1(clock, j, kf, q, qp);


	//####### setting test cases #######
	parameter testcase = 24'b001101011111011111011111;
	
	reg [2:0] k = 0;
	assign {clock, j, kf} = k;

	//##################################
	//####### run test cases ###########
	//##################################
	integer nTestbit = $bits(k);
	integer nTestcase = $bits(testcase)/$bits(k);
	integer loop1, loop2;

	initial begin

		$dumpfile("flipflop.vcd");
		$dumpvars(0, flipflop);
		$display("__________________________");

		for(loop1=nTestcase-1;loop1>=0;loop1=loop1-1) begin
			for(loop2=0;loop2<nTestbit;loop2=loop2+1) begin
				k[loop2] = testcase[nTestbit*loop1+loop2];
			end
			#10 $display("k = %b", k);
		end

		$finish;

	end

	//##################################

endmodule

flipflop.vcd
$date
	Fri Sep 08 22:32:55 2017
$end
$version
	Icarus Verilog
$end
$timescale
	100ps
$end
$scope module flipflop $end
$var wire 1 ! qp $end
$var wire 1 " q $end
$var wire 1 # kf $end
$var wire 1 $ j $end
$var wire 1 % clock $end
$var reg 3 & k [2:0] $end
$var integer 32 ' loop1 [31:0] $end
$var integer 32 ( loop2 [31:0] $end
$var integer 32 ) nTestbit [31:0] $end
$var integer 32 * nTestcase [31:0] $end
$scope module J1 $end
$var wire 1 % clock $end
$var wire 1 $ j $end
$var wire 1 # k $end
$var wire 1 ! qp $end
$var wire 1 " q $end
$var wire 1 + k1 $end
$var wire 1 , j1 $end
$var wire 1 - d $end
$scope module A1 $end
$var wire 1 $ i1 $end
$var wire 1 , o $end
$var wire 1 ! i2 $end
$upscope $end
$scope module A2 $end
$var wire 1 . i1 $end
$var wire 1 + o $end
$var wire 1 " i2 $end
$upscope $end
$scope module D1 $end
$var wire 1 % clock $end
$var wire 1 ! qp $end
$var wire 1 " q $end
$var wire 1 / d2 $end
$var wire 1 - d $end
$scope module D1 $end
$var wire 1 0 clock $end
$var wire 1 1 s $end
$var wire 1 2 r $end
$var wire 1 3 qp $end
$var wire 1 / q $end
$var wire 1 - d $end
$scope module A1 $end
$var wire 1 0 i1 $end
$var wire 1 1 o $end
$var wire 1 - i2 $end
$upscope $end
$scope module A2 $end
$var wire 1 0 i1 $end
$var wire 1 4 i2 $end
$var wire 1 2 o $end
$upscope $end
$scope module S1 $end
$var wire 1 5 clr $end
$var wire 1 6 pre $end
$var wire 1 / q $end
$var wire 1 3 qp $end
$var wire 1 2 r $end
$var wire 1 1 s $end
$upscope $end
$upscope $end
$scope module D2 $end
$var wire 1 % clock $end
$var wire 1 / d $end
$var wire 1 7 s $end
$var wire 1 8 r $end
$var wire 1 ! qp $end
$var wire 1 " q $end
$scope module A1 $end
$var wire 1 % i1 $end
$var wire 1 / i2 $end
$var wire 1 7 o $end
$upscope $end
$scope module A2 $end
$var wire 1 % i1 $end
$var wire 1 9 i2 $end
$var wire 1 8 o $end
$upscope $end
$scope module S1 $end
$var wire 1 : clr $end
$var wire 1 ; pre $end
$var wire 1 " q $end
$var wire 1 ! qp $end
$var wire 1 8 r $end
$var wire 1 7 s $end
$upscope $end
$upscope $end
$upscope $end
$scope module O1 $end
$var wire 1 , i1 $end
$var wire 1 + i2 $end
$var wire 1 - o $end
$upscope $end
$upscope $end
$upscope $end
$enddefinitions $end
#0
$dumpvars
z;
z:
19
08
07
z6
z5
14
x3
12
01
10
0/
0.
0-
0,
0+
b1000 *
b11 )
b11 (
b111 '
b1 &
0%
0$
1#
x"
x!
$end
#10
x9
x7
x/
02
x"
00
x8
1%
b101 &
b11 (
b110 '
#20
x9
x/
x4
x1
x2
x-
10
07
08
x,
0%
1$
b11 &
b11 (
b101 '
#30
01
02
00
x7
x8
1%
b111 &
b11 (
b100 '
#40
x1
x2
10
07
08
0%
b11 &
b11 (
b11 '
#50
01
02
00
x7
x8
1%
b111 &
b11 (
b10 '
#60
x1
x2
10
07
08
0%
b11 &
b11 (
b1 '
#70
01
02
00
x7
x8
1%
b111 &
b11 (
b0 '
#80
b11111111111111111111111111111111 '
