nov8.v
module fns(input clk, input rst, output[3:0] state);
	reg[3:0] state;
	always @(posedge clk or posedge rst) begin
		if (rst) begin
			state = 4'b0000;
		end
		else begin
			case(state)
				4'b0000: state = 4'b0001;
				4'b0001: state = 4'b0010;
				4'b0010: state = 4'b0011;
				4'b0011: state = 4'b0100;
				4'b0100: state = 4'b0101;
				4'b0101: state = 4'b0110;
				4'b0110: state = 4'b0000;
			endcase
		end
	end
endmodule

module t_fns();
	reg clk, rst;
	wire[3:0] state;
	fns F1(clk, rst, state);

	initial begin
		$dumpfile("nov8.vcd");
		$dumpvars(0, t_fns);
		
		clk = 1'b0;
		
		$monitor("state = %b", state);
		
		#5 rst = 1'b1;
		#5 rst = 1'b0;
		#5 clk = ~clk;
		#5 clk = ~clk;
		#5 clk = ~clk;
		#5 clk = ~clk;
		#5 clk = ~clk;
		#5 clk = ~clk;
		#5 clk = ~clk;
		#5 clk = ~clk;
		#5 clk = ~clk;
		#5 clk = ~clk;
		#5 clk = ~clk;
		#5 clk = ~clk;
		#5 clk = ~clk;
		#5 clk = ~clk;
		#5 clk = ~clk;
	end
endmodule

nov8.vcd
$date
	Wed Nov 08 13:56:35 2017
$end
$version
	Icarus Verilog
$end
$timescale
	1s
$end
$scope module t_fns $end
$var wire 4 ! state [3:0] $end
$var reg 1 " clk $end
$var reg 1 # rst $end
$scope module F1 $end
$var wire 1 " clk $end
$var wire 1 # rst $end
$var reg 4 $ state [3:0] $end
$upscope $end
$upscope $end
$enddefinitions $end
#0
$dumpvars
bx $
x#
0"
bx !
$end
#5
b0 !
b0 $
1#
#10
0#
#15
b1 !
b1 $
1"
#20
0"
#25
b10 !
b10 $
1"
#30
0"
#35
b11 !
b11 $
1"
#40
0"
#45
b100 !
b100 $
1"
#50
0"
#55
b101 !
b101 $
1"
#60
0"
#65
b110 !
b110 $
1"
#70
0"
#75
b0 !
b0 $
1"
#80
0"
#85
b1 !
b1 $
1"
