ROM.v
module ROM(
	input wire[15:0] address,
	output reg[5:0] data
);
	
	(* rom_style = "block" *)

	always @*
	case(address)
	16'h0000:data=6'b000000;
    16'h0001:data=6'b000000;
    16'h0002:data=6'b010100;
    16'h0003:data=6'b111000;
    16'h0004:data=6'b001010;
    16'h0005:data=6'b101000;
    16'h0006:data=6'b001001;
    16'h0007:data=6'b001011;
    16'h0008:data=6'b111001;
    16'h0009:data=6'b000100;
    16'h000a:data=6'b110000;
    16'h000b:data=6'b111010;
    16'h000c:data=6'b100010;
    16'h000d:data=6'b101011;
    16'h000e:data=6'b100100;
    16'h000f:data=6'b100010;
    16'h0010:data=6'b100011;
    16'h0011:data=6'b110001;
    16'h0012:data=6'b101000;
    16'h0013:data=6'b101010;
    16'h0014:data=6'b111000;
    16'h0015:data=6'b000011;
    16'h0016:data=6'b110110;
    16'h0017:data=6'b000001;
    16'h0018:data=6'b111000;
    16'h0019:data=6'b000011;
    16'h001a:data=6'b111000;
    16'h001b:data=6'b001010;
    16'h001c:data=6'b101000;
    16'h001d:data=6'b000011;
    16'h001e:data=6'b001000;
    16'h001f:data=6'b001000;
    16'h0020:data=6'b001001;
    16'h0021:data=6'b001011;
    16'h0022:data=6'b111001;
    16'h0023:data=6'b000100;
    16'h0024:data=6'b000100;
    16'h0025:data=6'b011000;
    16'h0026:data=6'b000011;
    16'h0027:data=6'b111000;
    16'h0028:data=6'b001010;
    16'h0029:data=6'b101000;
    16'h002a:data=6'b000101;
    16'h002b:data=6'b000000;
    16'h002c:data=6'b001000;
    16'h002d:data=6'b001001;
    16'h002e:data=6'b001011;
    16'h002f:data=6'b111001;
    16'h0030:data=6'b000100;
    16'h0031:data=6'b000101;
    16'h0032:data=6'b101000;
    16'h0033:data=6'b001000;
    16'h0034:data=6'b100010;
    16'h0035:data=6'b100011;
    16'h0036:data=6'b110001;
    16'h0037:data=6'b101000;
    16'h0038:data=6'b000110;
    16'h0039:data=6'b001011;
    16'h003a:data=6'b001000;
    16'h003b:data=6'b101010;
    16'h003c:data=6'b111000;
    16'h003d:data=6'b000011;
    16'h003e:data=6'b110110;
    16'h003f:data=6'b000111;
    16'h0040:data=6'b100000;
    16'h0041:data=6'b001001;
    16'h0042:data=6'b100100;
    16'h0043:data=6'b100010;
    16'h0044:data=6'b100011;
    16'h0045:data=6'b110001;
    16'h0046:data=6'b101000;
    16'h0047:data=6'b101010;
    16'h0048:data=6'b111000;
    16'h0049:data=6'b000011;
    16'h004a:data=6'b110110;
    16'h004b:data=6'b001000;
    16'h004c:data=6'b110000;
    16'h004d:data=6'b001011;
    16'h004e:data=6'b111000;
    16'h004f:data=6'b001010;
    16'h0050:data=6'b101000;
    16'h0051:data=6'b001001;
    16'h0052:data=6'b001011;
    16'h0053:data=6'b111001;
    16'h0054:data=6'b000100;
    16'h0055:data=6'b110000;
    16'h0056:data=6'b111010;
    16'h0057:data=6'b100010;
    16'h0058:data=6'b101011;
    16'h0059:data=6'b001010;
    16'h005a:data=6'b000000;
    16'h005b:data=6'b001001;
    16'h005c:data=6'b100100;
    16'h005d:data=6'b100010;
    16'h005e:data=6'b100011;
    16'h005f:data=6'b110001;
    16'h0060:data=6'b101000;
    16'h0061:data=6'b101010;
    16'h0062:data=6'b111000;
    16'h0063:data=6'b000011;
    16'h0064:data=6'b110110;
    16'h0065:data=6'b001011;
    16'h0066:data=6'b010000;
    16'h0067:data=6'b001011;
    16'h0068:data=6'b111000;
    16'h0069:data=6'b001010;
    16'h006a:data=6'b101000;
    16'h006b:data=6'b001001;
    16'h006c:data=6'b001011;
    16'h006d:data=6'b111001;
    16'h006e:data=6'b000100;
    16'h006f:data=6'b110000;
    16'h0070:data=6'b111010;
    16'h0071:data=6'b100010;
    16'h0072:data=6'b101011;
    16'h0073:data=6'b011001;
    16'h0074:data=6'b000000;
    16'h0075:data=6'b010100;
    16'h0076:data=6'b111000;
    16'h0077:data=6'b001010;
    16'h0078:data=6'b101000;
    16'h0079:data=6'b001001;
    16'h007a:data=6'b001011;
    16'h007b:data=6'b111001;
    16'h007c:data=6'b000100;
    16'h007d:data=6'b110000;
    16'h007e:data=6'b111010;
    16'h007f:data=6'b100010;
    16'h0080:data=6'b101011;
    16'h0081:data=6'b100100;
    16'h0082:data=6'b100010;
    16'h0083:data=6'b100011;
    16'h0084:data=6'b110001;
    16'h0085:data=6'b101000;
    16'h0086:data=6'b101010;
    16'h0087:data=6'b111000;
    16'h0088:data=6'b000011;
    16'h0089:data=6'b110110;
	default :data=6'b111111;
	endcase

	// reg[15:0] address_reg = 16'h0000;
	// assign address = address_reg;
	// initial begin
	// 	#10
	// 	$display("%b",data);
	// end
endmodule

PLAY.v
`include "ROM.v"

module PLAY(
	input wire clock_play,
	input wire restart,
	input wire[3:0] song_no,
	output reg[5:0] rgb_signal = 6'b110011
);
	reg[15:0] address_temp = 16'h0000;
	reg[11:0] iTime = 12'h000;
	reg[1:0] iPhase = 2'b00;
	reg[5:0] key_msb = 6'o00;
	reg[5:0] key_lsb = 6'o00;
	reg[5:0] nColor = 6'o00;
	reg[15:0] address;
	wire[5:0] data;
	wire[11:0] keyTime;
	time seed;
	assign keyTime = {key_msb,key_lsb};

	ROM R1(address,data);

	always @(posedge clock_play) begin
		if (restart) begin
			iTime <= 12'h000;
			iPhase <= 2'b00;
			address <= {2'b00,4'b0,10'b0000000000};
			rgb_signal <= 6'b110011;
		end
		else begin
			case(iPhase)
				2'b00: begin
					key_msb <= data;
					address <= address+1;
				end
				2'b01: begin
					key_lsb <= data;
					address <= address+1;
				end
				2'b10: begin
					nColor <= data;
					address_temp <= address;
					address <= address+1;
				end
				2'b11: begin
				    if (iTime>=keyTime) begin
				        rgb_signal <= data;
                        address <= address_temp+1+nColor;
				    end
				end
			endcase

			if(keyTime==12'hfff&&iPhase==2'b11)
				iPhase <= 2'b11;
			else if (iPhase==2'b00||iPhase==2'b01||iPhase==2'b10)
				iPhase <= iPhase+1;
			else if (iTime>=keyTime)
				iPhase <= 2'b00;

			iTime <= iTime+1;
		end
	end
	reg clk=1'b0;
	reg rst=1'b1;
	integer i;
	assign clock_play = clk;
	assign restart = rst;

	initial begin
		$dumpfile("PLAY.vcd");
		$dumpvars(0, PLAY);
		#10 clk=~clk;#10 clk=~clk;#10 clk=~clk;#10 clk=~clk;#10 clk=~clk;#10 clk=~clk;#10 clk=~clk;rst=~rst;
		for(i=0;i<32'h660;i=i+1)
			#10 clk=~clk;
	end
	//A14 B15 K17
endmodule

PLAY.vcd
$date
	Thu Dec 07 02:11:52 2017
$end
$version
	Icarus Verilog
$end
$timescale
	1s
$end
$scope module PLAY $end
$var wire 1 ! clock_play $end
$var wire 1 " restart $end
$var wire 4 # song_no [3:0] $end
$var wire 12 $ keyTime [11:0] $end
$var wire 6 % data [5:0] $end
$var reg 16 & address [15:0] $end
$var reg 16 ' address_temp [15:0] $end
$var reg 1 ( clk $end
$var reg 2 ) iPhase [1:0] $end
$var reg 12 * iTime [11:0] $end
$var reg 6 + key_lsb [5:0] $end
$var reg 6 , key_msb [5:0] $end
$var reg 6 - nColor [5:0] $end
$var reg 6 . rgb_signal [5:0] $end
$var reg 1 / rst $end
$var integer 32 0 i [31:0] $end
$scope module R1 $end
$var wire 16 1 address [15:0] $end
$var reg 6 2 data [5:0] $end
$upscope $end
$upscope $end
$enddefinitions $end
#0
$dumpvars
bx 2
bx 1
bx 0
1/
b110011 .
b0 -
b0 ,
b0 +
b0 *
b0 )
0(
b0 '
bx &
bx %
b0 $
bz #
1"
0!
$end
#10
b0 %
b0 2
b0 &
b0 1
1!
1(
#20
0!
0(
#30
1!
1(
#40
0!
0(
#50
1!
1(
#60
0!
0(
#70
b1 *
b1 )
b1 &
b1 1
b0 0
0"
0/
1!
1(
#80
b1 0
0!
0(
#90
b10100 %
b10100 2
b10 *
b10 )
b10 &
b10 1
b10 0
1!
1(
#100
b11 0
0!
0(
#110
b111000 %
b111000 2
b11 *
b11 )
b11 &
b11 1
b10 '
b10100 -
b100 0
1!
1(
#120
b101 0
0!
0(
#130
b1 %
b1 2
b100 *
b0 )
b10111 &
b10111 1
b111000 .
b110 0
1!
1(
#140
b111 0
0!
0(
#150
b111000 %
b111000 2
b101 *
b1 )
b11000 &
b11000 1
b1000000 $
b1 ,
b1000 0
1!
1(
#160
b1001 0
0!
0(
#170
b11 %
b11 2
b110 *
b10 )
b11001 &
b11001 1
b1111000 $
b111000 +
b1010 0
1!
1(
#180
b1011 0
0!
0(
#190
b111000 %
b111000 2
b111 *
b11 )
b11010 &
b11010 1
b11001 '
b11 -
b1100 0
1!
1(
#200
b1101 0
0!
0(
#210
b1000 *
b1110 0
1!
1(
#220
b1111 0
0!
0(
#230
b1001 *
b10000 0
1!
1(
#240
b10001 0
0!
0(
#250
b1010 *
b10010 0
1!
1(
#260
b10011 0
0!
0(
#270
b1011 *
b10100 0
1!
1(
#280
b10101 0
0!
0(
#290
b1100 *
b10110 0
1!
1(
#300
b10111 0
0!
0(
#310
b1101 *
b11000 0
1!
1(
#320
b11001 0
0!
0(
#330
b1110 *
b11010 0
1!
1(
#340
b11011 0
0!
0(
#350
b1111 *
b11100 0
1!
1(
#360
b11101 0
0!
0(
#370
b10000 *
b11110 0
1!
1(
#380
b11111 0
0!
0(
#390
b10001 *
b100000 0
1!
1(
#400
b100001 0
0!
0(
#410
b10010 *
b100010 0
1!
1(
#420
b100011 0
0!
0(
#430
b10011 *
b100100 0
1!
1(
#440
b100101 0
0!
0(
#450
b10100 *
b100110 0
1!
1(
#460
b100111 0
0!
0(
#470
b10101 *
b101000 0
1!
1(
#480
b101001 0
0!
0(
#490
b10110 *
b101010 0
1!
1(
#500
b101011 0
0!
0(
#510
b10111 *
b101100 0
1!
1(
#520
b101101 0
0!
0(
#530
b11000 *
b101110 0
1!
1(
#540
b101111 0
0!
0(
#550
b11001 *
b110000 0
1!
1(
#560
b110001 0
0!
0(
#570
b11010 *
b110010 0
1!
1(
#580
b110011 0
0!
0(
#590
b11011 *
b110100 0
1!
1(
#600
b110101 0
0!
0(
#610
b11100 *
b110110 0
1!
1(
#620
b110111 0
0!
0(
#630
b11101 *
b111000 0
1!
1(
#640
b111001 0
0!
0(
#650
b11110 *
b111010 0
1!
1(
#660
b111011 0
0!
0(
#670
b11111 *
b111100 0
1!
1(
#680
b111101 0
0!
0(
#690
b100000 *
b111110 0
1!
1(
#700
b111111 0
0!
0(
#710
b100001 *
b1000000 0
1!
1(
#720
b1000001 0
0!
0(
#730
b100010 *
b1000010 0
1!
1(
#740
b1000011 0
0!
0(
#750
b100011 *
b1000100 0
1!
1(
#760
b1000101 0
0!
0(
#770
b100100 *
b1000110 0
1!
1(
#780
b1000111 0
0!
0(
#790
b100101 *
b1001000 0
1!
1(
#800
b1001001 0
0!
0(
#810
b100110 *
b1001010 0
1!
1(
#820
b1001011 0
0!
0(
#830
b100111 *
b1001100 0
1!
1(
#840
b1001101 0
0!
0(
#850
b101000 *
b1001110 0
1!
1(
#860
b1001111 0
0!
0(
#870
b101001 *
b1010000 0
1!
1(
#880
b1010001 0
0!
0(
#890
b101010 *
b1010010 0
1!
1(
#900
b1010011 0
0!
0(
#910
b101011 *
b1010100 0
1!
1(
#920
b1010101 0
0!
0(
#930
b101100 *
b1010110 0
1!
1(
#940
b1010111 0
0!
0(
#950
b101101 *
b1011000 0
1!
1(
#960
b1011001 0
0!
0(
#970
b101110 *
b1011010 0
1!
1(
#980
b1011011 0
0!
0(
#990
b101111 *
b1011100 0
1!
1(
#1000
b1011101 0
0!
0(
#1010
b110000 *
b1011110 0
1!
1(
#1020
b1011111 0
0!
0(
#1030
b110001 *
b1100000 0
1!
1(
#1040
b1100001 0
0!
0(
#1050
b110010 *
b1100010 0
1!
1(
#1060
b1100011 0
0!
0(
#1070
b110011 *
b1100100 0
1!
1(
#1080
b1100101 0
0!
0(
#1090
b110100 *
b1100110 0
1!
1(
#1100
b1100111 0
0!
0(
#1110
b110101 *
b1101000 0
1!
1(
#1120
b1101001 0
0!
0(
#1130
b110110 *
b1101010 0
1!
1(
#1140
b1101011 0
0!
0(
#1150
b110111 *
b1101100 0
1!
1(
#1160
b1101101 0
0!
0(
#1170
b111000 *
b1101110 0
1!
1(
#1180
b1101111 0
0!
0(
#1190
b111001 *
b1110000 0
1!
1(
#1200
b1110001 0
0!
0(
#1210
b111010 *
b1110010 0
1!
1(
#1220
b1110011 0
0!
0(
#1230
b111011 *
b1110100 0
1!
1(
#1240
b1110101 0
0!
0(
#1250
b111100 *
b1110110 0
1!
1(
#1260
b1110111 0
0!
0(
#1270
b111101 *
b1111000 0
1!
1(
#1280
b1111001 0
0!
0(
#1290
b111110 *
b1111010 0
1!
1(
#1300
b1111011 0
0!
0(
#1310
b111111 *
b1111100 0
1!
1(
#1320
b1111101 0
0!
0(
#1330
b1000000 *
b1111110 0
1!
1(
#1340
b1111111 0
0!
0(
#1350
b1000001 *
b10000000 0
1!
1(
#1360
b10000001 0
0!
0(
#1370
b1000010 *
b10000010 0
1!
1(
#1380
b10000011 0
0!
0(
#1390
b1000011 *
b10000100 0
1!
1(
#1400
b10000101 0
0!
0(
#1410
b1000100 *
b10000110 0
1!
1(
#1420
b10000111 0
0!
0(
#1430
b1000101 *
b10001000 0
1!
1(
#1440
b10001001 0
0!
0(
#1450
b1000110 *
b10001010 0
1!
1(
#1460
b10001011 0
0!
0(
#1470
b1000111 *
b10001100 0
1!
1(
#1480
b10001101 0
0!
0(
#1490
b1001000 *
b10001110 0
1!
1(
#1500
b10001111 0
0!
0(
#1510
b1001001 *
b10010000 0
1!
1(
#1520
b10010001 0
0!
0(
#1530
b1001010 *
b10010010 0
1!
1(
#1540
b10010011 0
0!
0(
#1550
b1001011 *
b10010100 0
1!
1(
#1560
b10010101 0
0!
0(
#1570
b1001100 *
b10010110 0
1!
1(
#1580
b10010111 0
0!
0(
#1590
b1001101 *
b10011000 0
1!
1(
#1600
b10011001 0
0!
0(
#1610
b1001110 *
b10011010 0
1!
1(
#1620
b10011011 0
0!
0(
#1630
b1001111 *
b10011100 0
1!
1(
#1640
b10011101 0
0!
0(
#1650
b1010000 *
b10011110 0
1!
1(
#1660
b10011111 0
0!
0(
#1670
b1010001 *
b10100000 0
1!
1(
#1680
b10100001 0
0!
0(
#1690
b1010010 *
b10100010 0
1!
1(
#1700
b10100011 0
0!
0(
#1710
b1010011 *
b10100100 0
1!
1(
#1720
b10100101 0
0!
0(
#1730
b1010100 *
b10100110 0
1!
1(
#1740
b10100111 0
0!
0(
#1750
b1010101 *
b10101000 0
1!
1(
#1760
b10101001 0
0!
0(
#1770
b1010110 *
b10101010 0
1!
1(
#1780
b10101011 0
0!
0(
#1790
b1010111 *
b10101100 0
1!
1(
#1800
b10101101 0
0!
0(
#1810
b1011000 *
b10101110 0
1!
1(
#1820
b10101111 0
0!
0(
#1830
b1011001 *
b10110000 0
1!
1(
#1840
b10110001 0
0!
0(
#1850
b1011010 *
b10110010 0
1!
1(
#1860
b10110011 0
0!
0(
#1870
b1011011 *
b10110100 0
1!
1(
#1880
b10110101 0
0!
0(
#1890
b1011100 *
b10110110 0
1!
1(
#1900
b10110111 0
0!
0(
#1910
b1011101 *
b10111000 0
1!
1(
#1920
b10111001 0
0!
0(
#1930
b1011110 *
b10111010 0
1!
1(
#1940
b10111011 0
0!
0(
#1950
b1011111 *
b10111100 0
1!
1(
#1960
b10111101 0
0!
0(
#1970
b1100000 *
b10111110 0
1!
1(
#1980
b10111111 0
0!
0(
#1990
b1100001 *
b11000000 0
1!
1(
#2000
b11000001 0
0!
0(
#2010
b1100010 *
b11000010 0
1!
1(
#2020
b11000011 0
0!
0(
#2030
b1100011 *
b11000100 0
1!
1(
#2040
b11000101 0
0!
0(
#2050
b1100100 *
b11000110 0
1!
1(
#2060
b11000111 0
0!
0(
#2070
b1100101 *
b11001000 0
1!
1(
#2080
b11001001 0
0!
0(
#2090
b1100110 *
b11001010 0
1!
1(
#2100
b11001011 0
0!
0(
#2110
b1100111 *
b11001100 0
1!
1(
#2120
b11001101 0
0!
0(
#2130
b1101000 *
b11001110 0
1!
1(
#2140
b11001111 0
0!
0(
#2150
b1101001 *
b11010000 0
1!
1(
#2160
b11010001 0
0!
0(
#2170
b1101010 *
b11010010 0
1!
1(
#2180
b11010011 0
0!
0(
#2190
b1101011 *
b11010100 0
1!
1(
#2200
b11010101 0
0!
0(
#2210
b1101100 *
b11010110 0
1!
1(
#2220
b11010111 0
0!
0(
#2230
b1101101 *
b11011000 0
1!
1(
#2240
b11011001 0
0!
0(
#2250
b1101110 *
b11011010 0
1!
1(
#2260
b11011011 0
0!
0(
#2270
b1101111 *
b11011100 0
1!
1(
#2280
b11011101 0
0!
0(
#2290
b1110000 *
b11011110 0
1!
1(
#2300
b11011111 0
0!
0(
#2310
b1110001 *
b11100000 0
1!
1(
#2320
b11100001 0
0!
0(
#2330
b1110010 *
b11100010 0
1!
1(
#2340
b11100011 0
0!
0(
#2350
b1110011 *
b11100100 0
1!
1(
#2360
b11100101 0
0!
0(
#2370
b1110100 *
b11100110 0
1!
1(
#2380
b11100111 0
0!
0(
#2390
b1110101 *
b11101000 0
1!
1(
#2400
b11101001 0
0!
0(
#2410
b1110110 *
b11101010 0
1!
1(
#2420
b11101011 0
0!
0(
#2430
b1110111 *
b11101100 0
1!
1(
#2440
b11101101 0
0!
0(
#2450
b1111000 *
b11101110 0
1!
1(
#2460
b11101111 0
0!
0(
#2470
b11 %
b11 2
b1111001 *
b0 )
b11101 &
b11101 1
b11110000 0
1!
1(
#2480
b11110001 0
0!
0(
#2490
b1000 %
b1000 2
b1111010 *
b1 )
b11110 &
b11110 1
b11111000 $
b11 ,
b11110010 0
1!
1(
#2500
b11110011 0
0!
0(
#2510
b1111011 *
b10 )
b11111 &
b11111 1
b11001000 $
b1000 +
b11110100 0
1!
1(
#2520
b11110101 0
0!
0(
#2530
b1001 %
b1001 2
b1111100 *
b11 )
b100000 &
b100000 1
b11111 '
b1000 -
b11110110 0
1!
1(
#2540
b11110111 0
0!
0(
#2550
b1111101 *
b11111000 0
1!
1(
#2560
b11111001 0
0!
0(
#2570
b1111110 *
b11111010 0
1!
1(
#2580
b11111011 0
0!
0(
#2590
b1111111 *
b11111100 0
1!
1(
#2600
b11111101 0
0!
0(
#2610
b10000000 *
b11111110 0
1!
1(
#2620
b11111111 0
0!
0(
#2630
b10000001 *
b100000000 0
1!
1(
#2640
b100000001 0
0!
0(
#2650
b10000010 *
b100000010 0
1!
1(
#2660
b100000011 0
0!
0(
#2670
b10000011 *
b100000100 0
1!
1(
#2680
b100000101 0
0!
0(
#2690
b10000100 *
b100000110 0
1!
1(
#2700
b100000111 0
0!
0(
#2710
b10000101 *
b100001000 0
1!
1(
#2720
b100001001 0
0!
0(
#2730
b10000110 *
b100001010 0
1!
1(
#2740
b100001011 0
0!
0(
#2750
b10000111 *
b100001100 0
1!
1(
#2760
b100001101 0
0!
0(
#2770
b10001000 *
b100001110 0
1!
1(
#2780
b100001111 0
0!
0(
#2790
b10001001 *
b100010000 0
1!
1(
#2800
b100010001 0
0!
0(
#2810
b10001010 *
b100010010 0
1!
1(
#2820
b100010011 0
0!
0(
#2830
b10001011 *
b100010100 0
1!
1(
#2840
b100010101 0
0!
0(
#2850
b10001100 *
b100010110 0
1!
1(
#2860
b100010111 0
0!
0(
#2870
b10001101 *
b100011000 0
1!
1(
#2880
b100011001 0
0!
0(
#2890
b10001110 *
b100011010 0
1!
1(
#2900
b100011011 0
0!
0(
#2910
b10001111 *
b100011100 0
1!
1(
#2920
b100011101 0
0!
0(
#2930
b10010000 *
b100011110 0
1!
1(
#2940
b100011111 0
0!
0(
#2950
b10010001 *
b100100000 0
1!
1(
#2960
b100100001 0
0!
0(
#2970
b10010010 *
b100100010 0
1!
1(
#2980
b100100011 0
0!
0(
#2990
b10010011 *
b100100100 0
1!
1(
#3000
b100100101 0
0!
0(
#3010
b10010100 *
b100100110 0
1!
1(
#3020
b100100111 0
0!
0(
#3030
b10010101 *
b100101000 0
1!
1(
#3040
b100101001 0
0!
0(
#3050
b10010110 *
b100101010 0
1!
1(
#3060
b100101011 0
0!
0(
#3070
b10010111 *
b100101100 0
1!
1(
#3080
b100101101 0
0!
0(
#3090
b10011000 *
b100101110 0
1!
1(
#3100
b100101111 0
0!
0(
#3110
b10011001 *
b100110000 0
1!
1(
#3120
b100110001 0
0!
0(
#3130
b10011010 *
b100110010 0
1!
1(
#3140
b100110011 0
0!
0(
#3150
b10011011 *
b100110100 0
1!
1(
#3160
b100110101 0
0!
0(
#3170
b10011100 *
b100110110 0
1!
1(
#3180
b100110111 0
0!
0(
#3190
b10011101 *
b100111000 0
1!
1(
#3200
b100111001 0
0!
0(
#3210
b10011110 *
b100111010 0
1!
1(
#3220
b100111011 0
0!
0(
#3230
b10011111 *
b100111100 0
1!
1(
#3240
b100111101 0
0!
0(
#3250
b10100000 *
b100111110 0
1!
1(
#3260
b100111111 0
0!
0(
#3270
b10100001 *
b101000000 0
1!
1(
#3280
b101000001 0
0!
0(
#3290
b10100010 *
b101000010 0
1!
1(
#3300
b101000011 0
0!
0(
#3310
b10100011 *
b101000100 0
1!
1(
#3320
b101000101 0
0!
0(
#3330
b10100100 *
b101000110 0
1!
1(
#3340
b101000111 0
0!
0(
#3350
b10100101 *
b101001000 0
1!
1(
#3360
b101001001 0
0!
0(
#3370
b10100110 *
b101001010 0
1!
1(
#3380
b101001011 0
0!
0(
#3390
b10100111 *
b101001100 0
1!
1(
#3400
b101001101 0
0!
0(
#3410
b10101000 *
b101001110 0
1!
1(
#3420
b101001111 0
0!
0(
#3430
b10101001 *
b101010000 0
1!
1(
#3440
b101010001 0
0!
0(
#3450
b10101010 *
b101010010 0
1!
1(
#3460
b101010011 0
0!
0(
#3470
b10101011 *
b101010100 0
1!
1(
#3480
b101010101 0
0!
0(
#3490
b10101100 *
b101010110 0
1!
1(
#3500
b101010111 0
0!
0(
#3510
b10101101 *
b101011000 0
1!
1(
#3520
b101011001 0
0!
0(
#3530
b10101110 *
b101011010 0
1!
1(
#3540
b101011011 0
0!
0(
#3550
b10101111 *
b101011100 0
1!
1(
#3560
b101011101 0
0!
0(
#3570
b10110000 *
b101011110 0
1!
1(
#3580
b101011111 0
0!
0(
#3590
b10110001 *
b101100000 0
1!
1(
#3600
b101100001 0
0!
0(
#3610
b10110010 *
b101100010 0
1!
1(
#3620
b101100011 0
0!
0(
#3630
b10110011 *
b101100100 0
1!
1(
#3640
b101100101 0
0!
0(
#3650
b10110100 *
b101100110 0
1!
1(
#3660
b101100111 0
0!
0(
#3670
b10110101 *
b101101000 0
1!
1(
#3680
b101101001 0
0!
0(
#3690
b10110110 *
b101101010 0
1!
1(
#3700
b101101011 0
0!
0(
#3710
b10110111 *
b101101100 0
1!
1(
#3720
b101101101 0
0!
0(
#3730
b10111000 *
b101101110 0
1!
1(
#3740
b101101111 0
0!
0(
#3750
b10111001 *
b101110000 0
1!
1(
#3760
b101110001 0
0!
0(
#3770
b10111010 *
b101110010 0
1!
1(
#3780
b101110011 0
0!
0(
#3790
b10111011 *
b101110100 0
1!
1(
#3800
b101110101 0
0!
0(
#3810
b10111100 *
b101110110 0
1!
1(
#3820
b101110111 0
0!
0(
#3830
b10111101 *
b101111000 0
1!
1(
#3840
b101111001 0
0!
0(
#3850
b10111110 *
b101111010 0
1!
1(
#3860
b101111011 0
0!
0(
#3870
b10111111 *
b101111100 0
1!
1(
#3880
b101111101 0
0!
0(
#3890
b11000000 *
b101111110 0
1!
1(
#3900
b101111111 0
0!
0(
#3910
b11000001 *
b110000000 0
1!
1(
#3920
b110000001 0
0!
0(
#3930
b11000010 *
b110000010 0
1!
1(
#3940
b110000011 0
0!
0(
#3950
b11000011 *
b110000100 0
1!
1(
#3960
b110000101 0
0!
0(
#3970
b11000100 *
b110000110 0
1!
1(
#3980
b110000111 0
0!
0(
#3990
b11000101 *
b110001000 0
1!
1(
#4000
b110001001 0
0!
0(
#4010
b11000110 *
b110001010 0
1!
1(
#4020
b110001011 0
0!
0(
#4030
b11000111 *
b110001100 0
1!
1(
#4040
b110001101 0
0!
0(
#4050
b11001000 *
b110001110 0
1!
1(
#4060
b110001111 0
0!
0(
#4070
b1010 %
b1010 2
b11001001 *
b0 )
b101000 &
b101000 1
b1001 .
b110010000 0
1!
1(
#4080
b110010001 0
0!
0(
#4090
b101000 %
b101000 2
b11001010 *
b1 )
b101001 &
b101001 1
b1010001000 $
b1010 ,
b110010010 0
1!
1(
#4100
b110010011 0
0!
0(
#4110
b101 %
b101 2
b11001011 *
b10 )
b101010 &
b101010 1
b1010101000 $
b101000 +
b110010100 0
1!
1(
#4120
b110010101 0
0!
0(
#4130
b0 %
b0 2
b11001100 *
b11 )
b101011 &
b101011 1
b101010 '
b101 -
b110010110 0
1!
1(
#4140
b110010111 0
0!
0(
#4150
b11001101 *
b110011000 0
1!
1(
#4160
b110011001 0
0!
0(
#4170
b11001110 *
b110011010 0
1!
1(
#4180
b110011011 0
0!
0(
#4190
b11001111 *
b110011100 0
1!
1(
#4200
b110011101 0
0!
0(
#4210
b11010000 *
b110011110 0
1!
1(
#4220
b110011111 0
0!
0(
#4230
b11010001 *
b110100000 0
1!
1(
#4240
b110100001 0
0!
0(
#4250
b11010010 *
b110100010 0
1!
1(
#4260
b110100011 0
0!
0(
#4270
b11010011 *
b110100100 0
1!
1(
#4280
b110100101 0
0!
0(
#4290
b11010100 *
b110100110 0
1!
1(
#4300
b110100111 0
0!
0(
#4310
b11010101 *
b110101000 0
1!
1(
#4320
b110101001 0
0!
0(
#4330
b11010110 *
b110101010 0
1!
1(
#4340
b110101011 0
0!
0(
#4350
b11010111 *
b110101100 0
1!
1(
#4360
b110101101 0
0!
0(
#4370
b11011000 *
b110101110 0
1!
1(
#4380
b110101111 0
0!
0(
#4390
b11011001 *
b110110000 0
1!
1(
#4400
b110110001 0
0!
0(
#4410
b11011010 *
b110110010 0
1!
1(
#4420
b110110011 0
0!
0(
#4430
b11011011 *
b110110100 0
1!
1(
#4440
b110110101 0
0!
0(
#4450
b11011100 *
b110110110 0
1!
1(
#4460
b110110111 0
0!
0(
#4470
b11011101 *
b110111000 0
1!
1(
#4480
b110111001 0
0!
0(
#4490
b11011110 *
b110111010 0
1!
1(
#4500
b110111011 0
0!
0(
#4510
b11011111 *
b110111100 0
1!
1(
#4520
b110111101 0
0!
0(
#4530
b11100000 *
b110111110 0
1!
1(
#4540
b110111111 0
0!
0(
#4550
b11100001 *
b111000000 0
1!
1(
#4560
b111000001 0
0!
0(
#4570
b11100010 *
b111000010 0
1!
1(
#4580
b111000011 0
0!
0(
#4590
b11100011 *
b111000100 0
1!
1(
#4600
b111000101 0
0!
0(
#4610
b11100100 *
b111000110 0
1!
1(
#4620
b111000111 0
0!
0(
#4630
b11100101 *
b111001000 0
1!
1(
#4640
b111001001 0
0!
0(
#4650
b11100110 *
b111001010 0
1!
1(
#4660
b111001011 0
0!
0(
#4670
b11100111 *
b111001100 0
1!
1(
#4680
b111001101 0
0!
0(
#4690
b11101000 *
b111001110 0
1!
1(
#4700
b111001111 0
0!
0(
#4710
b11101001 *
b111010000 0
1!
1(
#4720
b111010001 0
0!
0(
#4730
b11101010 *
b111010010 0
1!
1(
#4740
b111010011 0
0!
0(
#4750
b11101011 *
b111010100 0
1!
1(
#4760
b111010101 0
0!
0(
#4770
b11101100 *
b111010110 0
1!
1(
#4780
b111010111 0
0!
0(
#4790
b11101101 *
b111011000 0
1!
1(
#4800
b111011001 0
0!
0(
#4810
b11101110 *
b111011010 0
1!
1(
#4820
b111011011 0
0!
0(
#4830
b11101111 *
b111011100 0
1!
1(
#4840
b111011101 0
0!
0(
#4850
b11110000 *
b111011110 0
1!
1(
#4860
b111011111 0
0!
0(
#4870
b11110001 *
b111100000 0
1!
1(
#4880
b111100001 0
0!
0(
#4890
b11110010 *
b111100010 0
1!
1(
#4900
b111100011 0
0!
0(
#4910
b11110011 *
b111100100 0
1!
1(
#4920
b111100101 0
0!
0(
#4930
b11110100 *
b111100110 0
1!
1(
#4940
b111100111 0
0!
0(
#4950
b11110101 *
b111101000 0
1!
1(
#4960
b111101001 0
0!
0(
#4970
b11110110 *
b111101010 0
1!
1(
#4980
b111101011 0
0!
0(
#4990
b11110111 *
b111101100 0
1!
1(
#5000
b111101101 0
0!
0(
#5010
b11111000 *
b111101110 0
1!
1(
#5020
b111101111 0
0!
0(
#5030
b11111001 *
b111110000 0
1!
1(
#5040
b111110001 0
0!
0(
#5050
b11111010 *
b111110010 0
1!
1(
#5060
b111110011 0
0!
0(
#5070
b11111011 *
b111110100 0
1!
1(
#5080
b111110101 0
0!
0(
#5090
b11111100 *
b111110110 0
1!
1(
#5100
b111110111 0
0!
0(
#5110
b11111101 *
b111111000 0
1!
1(
#5120
b111111001 0
0!
0(
#5130
b11111110 *
b111111010 0
1!
1(
#5140
b111111011 0
0!
0(
#5150
b11111111 *
b111111100 0
1!
1(
#5160
b111111101 0
0!
0(
#5170
b100000000 *
b111111110 0
1!
1(
#5180
b111111111 0
0!
0(
#5190
b100000001 *
b1000000000 0
1!
1(
#5200
b1000000001 0
0!
0(
#5210
b100000010 *
b1000000010 0
1!
1(
#5220
b1000000011 0
0!
0(
#5230
b100000011 *
b1000000100 0
1!
1(
#5240
b1000000101 0
0!
0(
#5250
b100000100 *
b1000000110 0
1!
1(
#5260
b1000000111 0
0!
0(
#5270
b100000101 *
b1000001000 0
1!
1(
#5280
b1000001001 0
0!
0(
#5290
b100000110 *
b1000001010 0
1!
1(
#5300
b1000001011 0
0!
0(
#5310
b100000111 *
b1000001100 0
1!
1(
#5320
b1000001101 0
0!
0(
